sewerrat/__init__.py
sewerrat/_utils.py
sewerrat/deregister.py
sewerrat/list_fields.py
sewerrat/list_files.py
sewerrat/list_registered_directories.py
sewerrat/list_tokens.py
sewerrat/query.py
sewerrat/register.py
sewerrat/retrieve_directory.py
sewerrat/retrieve_file.py
sewerrat/retrieve_metadata.py
sewerrat/start_sewerrat.py
sewerrat-0.3.1.dist-info/licenses/LICENSE.txt
sewerrat-0.3.1.dist-info/METADATA
sewerrat-0.3.1.dist-info/WHEEL
sewerrat-0.3.1.dist-info/top_level.txt
sewerrat-0.3.1.dist-info/RECORD
