Metadata-Version: 2.4
Name: SewerRat
Version: 0.3.1
Summary: Python client for the SewerRat API
Home-page: https://github.com/ArtifactDB/SewerRat-py/
Author: LTLA
Author-email: infinite.monkeys.with.keyboards@gmail.com
License: MIT
Project-URL: Documentation, https://artifactdb.github.io/SewerRat-py/
Platform: any
Classifier: Development Status :: 4 - Beta
Classifier: Programming Language :: Python
License-File: LICENSE.txt
Requires-Dist: importlib-metadata; python_version < "3.8"
Requires-Dist: requests
Requires-Dist: appdirs
Provides-Extra: testing
Requires-Dist: setuptools; extra == "testing"
Requires-Dist: pytest; extra == "testing"
Requires-Dist: pytest-cov; extra == "testing"
Dynamic: license-file
